[
{
  "from": "style/*",
  "to": "style/*"
},
{
  "from": "vendor/*",
  "to": "vendor/*"
},
{
  "from": "script/*",
  "to": "script/*"
},
{
  "from": "_views/",
  "to": "../../../_views/",
  "query" : {
    "descending" : true,
    "limit" : 5,
    "front" : true
  }
},
{
  "from": "samedifference/*",
  "to": "../../../samedifference/*"
},
{
  "from": "/samedifference/*",
  "to": "../../../samedifference/*"
},
{
  "from": "/",
  "to": "index.html"
  
},
{
  "from": "",
  "to": "index.html"
},
{
  "from": "*",
  "to": "*"
}
]